code_size_counter/__init__.py
code_size_counter/code_size_counter.py
code_size_counter/file_tools.py
code_size_counter/main.py
code_size_counter-1.0.2.dist-info/entry_points.txt
code_size_counter-1.0.2.dist-info/LICENSE
code_size_counter-1.0.2.dist-info/METADATA
code_size_counter-1.0.2.dist-info/WHEEL
code_size_counter-1.0.2.dist-info/RECORD
