Metadata-Version: 2.1
Name: code-size-counter
Version: 1.0.2
Summary: Command line utility used for calculating total size (both KB and lines of code) of program's code.
Home-page: https://github.com/VL-CZ/code-size-counter
License: MIT
Keywords: lines of code,code size,KB size
Author: Vojtěch Lengál
Author-email: vojta.lengal@gmail.com
Requires-Python: >=3.9,<4.0
Classifier: License :: OSI Approved :: MIT License
Classifier: Programming Language :: Python :: 3
Classifier: Programming Language :: Python :: 3.9
Classifier: Programming Language :: Python :: 3.10
Classifier: Programming Language :: Python :: 3.11
Classifier: Programming Language :: Python :: 3.12
Requires-Dist: black (>=23.11.0,<24.0.0)
Requires-Dist: flake8 (>=6.1.0,<7.0.0)
Requires-Dist: prettytable (>=3.9.0,<4.0.0)
Project-URL: Documentation, https://github.com/VL-CZ/code-size-counter
Project-URL: Repository, https://github.com/VL-CZ/code-size-counter
